nbp_sdk/_exceptions.py
nbp_sdk/_request.py
nbp_sdk/_settings.py
nbp_sdk/_urls.py
nbp_sdk/_utils.py
nbp_sdk/client.py
nbp_sdk/models.py
nbp_sdk/types.py
nbp_sdk-0.1.6.dist-info/LICENSE
nbp_sdk-0.1.6.dist-info/METADATA
nbp_sdk-0.1.6.dist-info/WHEEL
nbp_sdk-0.1.6.dist-info/top_level.txt
nbp_sdk-0.1.6.dist-info/RECORD
