Metadata-Version: 2.1
Name: nbp-sdk
Version: 0.1.6
Summary: Plain simple SDK for Polish National Bank (NBP) currency rate
Author-email: Łukasz Klim <lukasz.klim92@gmail.com>
Project-URL: Homepage, https://github.com/lukas346/nbp_sdk
Project-URL: Issues, https://github.com/lukas346/nbp_sdk/issues
Classifier: Programming Language :: Python :: 3
Classifier: Programming Language :: Python :: 3.10
Classifier: Programming Language :: Python :: 3.11
Classifier: Programming Language :: Python :: 3.12
Classifier: Programming Language :: Python :: 3.13
Classifier: Operating System :: OS Independent
Requires-Python: >=3.10
License-File: LICENSE
Requires-Dist: requests >=2.31.0
